MANIFEST.in
README.md
setup.py
src/setuptools_epydoc/__init__.py
src/setuptools_epydoc.egg-info/PKG-INFO
src/setuptools_epydoc.egg-info/SOURCES.txt
src/setuptools_epydoc.egg-info/dependency_links.txt
src/setuptools_epydoc.egg-info/entry_points.txt
src/setuptools_epydoc.egg-info/not-zip-safe
src/setuptools_epydoc.egg-info/requires.txt
src/setuptools_epydoc.egg-info/top_level.txt