Metadata-Version: 1.1
Name: setuptools-epydoc
Version: 0.1
Summary: Epydoc API documentation generation command for pylint
Home-page: https://github.com/languitar/setuptools-epydoc
Author: Johannes Wienke
Author-email: languitar@semipol.de
License: MPL
Keywords: epydoc setuptools command
Platform: UNKNOWN
Classifier: Topic :: Documentation
Classifier: Framework :: Setuptools Plugin
Classifier: Development Status :: 4 - Beta
Classifier: Programming Language :: Python
Classifier: Intended Audience :: Developers
Classifier: Operating System :: OS Independent
Classifier: License :: OSI Approved :: Mozilla Public License 2.0 (MPL 2.0)
Classifier: Topic :: Software Development :: Documentation
Classifier: Topic :: Software Development :: Libraries :: Python Modules
